empyricalRMT/__init__.py
empyricalRMT/_constants.py
empyricalRMT/_eigvals.py
empyricalRMT/_types.py
empyricalRMT/_validate.py
empyricalRMT/brody.py
empyricalRMT/compare.py
empyricalRMT/construct.py
empyricalRMT/correlater.py
empyricalRMT/detrend.py
empyricalRMT/eigenvalues.py
empyricalRMT/ensemble.py
empyricalRMT/exponentials.py
empyricalRMT/observables/__init__.py
empyricalRMT/observables/levelvariance.py
empyricalRMT/observables/rigidity.py
empyricalRMT/observables/step.py
empyricalRMT/plot.py
empyricalRMT/signalproc/__init__.py
empyricalRMT/signalproc/clean.py
empyricalRMT/signalproc/detrend.py
empyricalRMT/smoother.py
empyricalRMT/trim.py
empyricalRMT/unfold.py
empyricalRMT/utils.py
empyricalrmt-1.1.1.dist-info/LICENSE
empyricalrmt-1.1.1.dist-info/WHEEL
empyricalrmt-1.1.1.dist-info/METADATA
empyricalrmt-1.1.1.dist-info/RECORD
