Metadata-Version: 2.1
Name: empyricalrmt
Version: 1.1.1
Summary: Eigenvalue unfolding and spectral observable computation
Author: Derek M Berger
Author-email: dmberger.dev@gmail.com
Requires-Python: >=3.10,<3.12
Classifier: Programming Language :: Python :: 3
Classifier: Programming Language :: Python :: 3.10
Requires-Dist: EMD-signal (>=1.2.3,<2.0.0)
Requires-Dist: matplotlib (>=3.5.3,<4.0.0)
Requires-Dist: numba (>=0.56.2,<0.57.0)
Requires-Dist: numpy (>=1.23.3,<2.0.0)
Requires-Dist: pandas (>=1.4.4,<2.0.0)
Requires-Dist: pyod (>=1.0.4,<2.0.0)
Requires-Dist: scikit-learn (>=1.1.2,<2.0.0)
Requires-Dist: scipy (>=1.9.1,<2.0.0)
Requires-Dist: seaborn (>=0.12.0,<0.13.0)
Requires-Dist: statsmodels (>=0.13.2,<0.14.0)
Requires-Dist: tqdm (>=4.64.1,<5.0.0)
Requires-Dist: typing-extensions (>=4.3.0,<5.0.0)
